mkmapi/__init__.py
mkmapi/api_request.py
mkmapi/env_variables.py
mkmapi/exceptions.py
mkmapi/mkm.py
mkmapi/mkm_oauth1_client.py
mkmapi/mkm_oauth1_serializer.py
mkmapi/mkm_xmlrequest_serializer.py
mkmapi/api_map/__init__.py
mkmapi/api_map/account_management.py
mkmapi/api_map/marketplace_info.py
mkmapi/api_map/order_management.py
mkmapi/api_map/shopping_cart_manipulation.py
mkmapi/api_map/stock_management.py
mkmapi/api_map/wants_list_management.py
mkmapi-1.0.3.dist-info/LICENSE.md
mkmapi-1.0.3.dist-info/METADATA
mkmapi-1.0.3.dist-info/WHEEL
mkmapi-1.0.3.dist-info/top_level.txt
mkmapi-1.0.3.dist-info/RECORD
