Metadata-Version: 2.1
Name: mkmapi
Version: 1.0.3
Summary: A full wrapper for the MKM API 2.0
Home-page: https://github.com/matnad/mkmapi
Author: Matthias Nadler
Author-email: matnad@gmail.com
License: MIT
Platform: UNKNOWN
